Tensorplow/D1.py
Tensorplow/D3.py
Tensorplow/D4.py
Tensorplow/D5.py
Tensorplow/D7.py
Tensorplow/D8.py
Tensorplow/M1.py
Tensorplow/M2.py
Tensorplow/M3.py
Tensorplow/M6.py
Tensorplow/M7.py
Tensorplow/M8.py
Tensorplow/__init__.py
tensorplow-0.1.dist-info/licenses/LICENSE.txt
tensorplow-0.1.dist-info/METADATA
tensorplow-0.1.dist-info/WHEEL
tensorplow-0.1.dist-info/top_level.txt
tensorplow-0.1.dist-info/RECORD
