Metadata-Version: 2.4
Name: tensorplow
Version: 0.1
Summary: Tensorplow is an open source machine learning framework for everyone.
Author: tensorplow
Author-email: tensorplow@dev.org
Classifier: Programming Language :: Python :: 3
Classifier: License :: OSI Approved :: MIT License
Classifier: Operating System :: OS Independent
License-File: LICENSE.txt
Dynamic: author
Dynamic: author-email
Dynamic: classifier
Dynamic: license-file
Dynamic: summary
